README.md
setup.py
apache_airflow_providers_cronitor.egg-info/PKG-INFO
apache_airflow_providers_cronitor.egg-info/SOURCES.txt
apache_airflow_providers_cronitor.egg-info/dependency_links.txt
apache_airflow_providers_cronitor.egg-info/entry_points.txt
apache_airflow_providers_cronitor.egg-info/requires.txt
apache_airflow_providers_cronitor.egg-info/top_level.txt
cronitor_airflow/__init__.py
cronitor_airflow/example_dags/__init__.py
cronitor_airflow/example_dags/cronitor_autodiscover.py
cronitor_airflow/hooks/__init__.py
cronitor_airflow/hooks/cronitor_hook.py
cronitor_airflow/operators/__init__.py
cronitor_airflow/operators/cronitor_operator.py