Metadata-Version: 1.1
Name: apache-airflow-providers-cronitor
Version: 0.0.1
Summary: Airflow plugin for Cronitor, with hook, operator, and auto-discovery
Home-page: https://github.com/cronitorio/cronitor-airflow
Author: JJ
Author-email: jj@cronitor.io
License: MIT
Platform: UNKNOWN
Classifier: Framework :: Apache Airflow
Classifier: Framework :: Apache Airflow :: Provider
